konverter/__init__.py
konverter/__main__.py
konverter/app.py
konverter/context.py
konverter/template.py
konverter/vault.py
konverter/yaml.py
konverter-0.3.0.dist-info/entry_points.txt
konverter-0.3.0.dist-info/LICENSE
konverter-0.3.0.dist-info/WHEEL
konverter-0.3.0.dist-info/METADATA
konverter-0.3.0.dist-info/RECORD
