Metadata-Version: 2.1
Name: konverter
Version: 0.3.0
Summary: YAML templating for responsible users
Home-page: https://github.com/westphahl/konverter
License: MIT
Keywords: yaml,template,kubernetes
Author: Simon Westphahl
Author-email: simon@westphahl.net
Requires-Python: >=3.7,<4.0
Classifier: License :: OSI Approved :: MIT License
Classifier: Programming Language :: Python :: 3
Classifier: Programming Language :: Python :: 3.7
Classifier: Programming Language :: Python :: 3.8
Requires-Dist: click (>=7.0,<8.0)
Requires-Dist: cryptography (>=2.8,<3.0)
Requires-Dist: jinja2 (>=2.10.3,<3.0.0)
Requires-Dist: ruamel.yaml (>=0.16.5,<0.17.0)
Project-URL: Documentation, https://github.com/westphahl/konverter/blob/master/README.md
Project-URL: Repository, https://github.com/westphahl/konverter
